README.md
setup.py
pulumi_youtrack/__init__.py
pulumi_youtrack/_utilities.py
pulumi_youtrack/provider.py
pulumi_youtrack/pulumi-plugin.json
pulumi_youtrack/py.typed
pulumi_youtrack/random.py
pulumi_youtrack.egg-info/PKG-INFO
pulumi_youtrack.egg-info/SOURCES.txt
pulumi_youtrack.egg-info/dependency_links.txt
pulumi_youtrack.egg-info/not-zip-safe
pulumi_youtrack.egg-info/requires.txt
pulumi_youtrack.egg-info/top_level.txt