Metadata-Version: 2.1
Name: pulumi-youtrack
Version: 0.0.7
License: Apache-2.0
Project-URL: Repository, https://github.com/oss4u/pulumi-youtrack-native
Requires-Python: >=3.8
